pktperf/__init__.py
pktperf/pktgen.py
pktperf/pktperf.py
pktperf/pktsar.py
pktperf-0.4.1.dist-info/LICENSE
pktperf-0.4.1.dist-info/METADATA
pktperf-0.4.1.dist-info/WHEEL
pktperf-0.4.1.dist-info/entry_points.txt
pktperf-0.4.1.dist-info/top_level.txt
pktperf-0.4.1.dist-info/RECORD
