Metadata-Version: 2.1
Name: pktperf
Version: 0.4.1
Summary: pktgen python scripts
Author: junka
Author-email: wan.junjie@fixmail.com
Project-URL: Bug Tracker, https://github.com/junka/pktperf/issues
Classifier: Programming Language :: Python :: 3
Classifier: License :: OSI Approved :: BSD License
Requires-Python: >=3.5
License-File: LICENSE
